Installing.md
MANIFEST.in
README.md
setup.py
titamu/__init__.py
titamu/disk.py
titamu/net.py
titamu/storagedomain.py
titamu/template.py
titamu/titamushell.py
titamu/utils.py
titamu/vm.py
titamu.egg-info/PKG-INFO
titamu.egg-info/SOURCES.txt
titamu.egg-info/dependency_links.txt
titamu.egg-info/requires.txt
titamu.egg-info/top_level.txt
titamu/bin/titamu