Metadata-Version: 2.1
Name: titamu
Version: 0.59
Summary: A command line tool to talk with RHV environment
Home-page: https://github.com/cchen666/titamu
Author: Chen Chen
Author-email: cchenlp@qq.com
License: BSD License
Platform: all
Classifier: Development Status :: 4 - Beta
Classifier: Operating System :: OS Independent
Classifier: Intended Audience :: Developers
Classifier: License :: OSI Approved :: BSD License
Classifier: Programming Language :: Python :: 2.7
Classifier: Topic :: Software Development :: Libraries
